{"name":"Validate navigation to the Claims page on clicking Claims","id":"validating-all-the-services-available-in-the-services-tab;validate-navigation-to-the-claims-page-on-clicking-claims","testSteps":[{"number":1,"description":"Given Services page","duration":8,"startTime":"2021-07-27T11:47:12.640556100+05:30[Asia/Calcutta]","result":"SUCCESS","precondition":false,"level":0},{"number":2,"description":"When Click claims page","duration":36,"startTime":"2021-07-27T11:47:12.651526500+05:30[Asia/Calcutta]","exception":{"errorType":"java.lang.NullPointerException","stackTrace":[{"declaringClass":"Stepdefinitions.Services_positive_scenario","methodName":"clickClaimsPage","fileName":"Services_positive_scenario.java","lineNumber":115},{"declaringClass":"✽","methodName":"Click claims page","fileName":"file:///D:/automation/MPH-IOS-main%20(1)/MPH-IOS-main/src/test/resources/features/Services_positive_scenario.feature","lineNumber":30}]},"result":"ERROR","precondition":false,"level":0},{"number":3,"description":"Then Verify Claims page","duration":8,"startTime":"2021-07-27T11:47:12.691424300+05:30[Asia/Calcutta]","result":"SKIPPED","precondition":false,"level":0}],"userStory":{"id":"validating-all-the-services-available-in-the-services-tab","storyName":"Validating all the services available in the services tab","path":"Services_positive_scenario.feature","type":"feature"},"featureTag":{"name":"Validating all the services available in the services tab","type":"feature","displayName":"Validating all the services available in the services tab"},"title":"Validate navigation to the Claims page on clicking Claims","description":"","tags":[{"name":"Validating all the services available in the services tab","type":"feature","displayName":"Validating all the services available in the services tab"}],"startTime":"2021-07-27T11:47:12.626594+05:30[Asia/Calcutta]","duration":79,"testFailureCause":{"errorType":"java.lang.NullPointerException","stackTrace":[{"declaringClass":"Stepdefinitions.Services_positive_scenario","methodName":"clickClaimsPage","fileName":"Services_positive_scenario.java","lineNumber":115},{"declaringClass":"✽","methodName":"Click claims page","fileName":"file:///D:/automation/MPH-IOS-main%20(1)/MPH-IOS-main/src/test/resources/features/Services_positive_scenario.feature","lineNumber":30}]},"testFailureClassname":"java.lang.NullPointerException","testFailureSummary":"ERROR;java.lang.NullPointerException;null;Services_positive_scenario.java","projectKey":"","annotatedResult":"ERROR","isManualTestingUpToDate":false,"manual":false,"testSource":"Cucumber","result":"ERROR"}